dtuf/__init__.py
dtuf/__main__.py
dtuf/exceptions.py
dtuf/main.py
python_dtuf-1.0.0.dist-info/DESCRIPTION.rst
python_dtuf-1.0.0.dist-info/METADATA
python_dtuf-1.0.0.dist-info/RECORD
python_dtuf-1.0.0.dist-info/WHEEL
python_dtuf-1.0.0.dist-info/entry_points.txt
python_dtuf-1.0.0.dist-info/metadata.json
python_dtuf-1.0.0.dist-info/top_level.txt
