Metadata-Version: 2.0
Name: python-dtuf
Version: 1.0.0
Summary: Docker registry bindings for The Update Framework
Home-page: https://github.com/davedoesdev/dtuf
Author: David Halls
Author-email: dave@davedoesdev.com
License: MIT
Keywords: docker registry tuf update framework
Platform: UNKNOWN
Requires-Dist: cryptography (>=1.1.2)
Requires-Dist: decorator (>=4.0.6)
Requires-Dist: fasteners (>=0.14.1)
Requires-Dist: iso8601 (>=0.1.11)
Requires-Dist: pycrypto (>=2.6.1)
Requires-Dist: python-dxf (>=3.0.0)
Requires-Dist: pytimeparse (>=1.1.5)
Requires-Dist: tqdm (>=3.1.4)
Requires-Dist: tuf (>=0.10.0)
